gitno/__init__.py
gitno/__main__.py
gitno/cli.py
gitno/main.py
gitno/version.py
gitno-0.1.3.dist-info/LICENSE
gitno-0.1.3.dist-info/METADATA
gitno-0.1.3.dist-info/WHEEL
gitno-0.1.3.dist-info/entry_points.txt
gitno-0.1.3.dist-info/top_level.txt
gitno-0.1.3.dist-info/RECORD
