Metadata-Version: 2.1
Name: gitno
Version: 0.1.3
Summary: A commandline gitignore generator
Author-email: Ian Andwati <andwatiian@gmail.com>
License: Copyright (c) 2023 Ian Andwati
Project-URL: homepage, https://github.com/andwati/gitno
Project-URL: documentation, https://github.com/andwati/gitno
Project-URL: repository, https://github.com/andwati/gitno.git
Project-URL: changelog, https://github.com/andwati/gitno
Keywords: git,gitignore,cli
Classifier: Programming Language :: Python :: 3
Classifier: License :: OSI Approved :: MIT License
Classifier: Operating System :: OS Independent
Classifier: Environment :: Console
Requires-Python: >=3.6
License-File: LICENSE
Requires-Dist: requests
Requires-Dist: click
Requires-Dist: tqdm
